src/__init__.py
src/imsdk/__init__.py
src/imsdk/engine.py
src/imsdk/util.py
src/lib/librust_universal_imsdk.dylib
src/lib/rcim_client.h
src/lib/rcim_client.py
src/lib/rcim_utils.py
src/lib/rust_db/RongCloud/global.kv
src/lib/rust_db/RongCloud/c9kqb3rdcj1rj/rc-log.db
src/lib/rust_db/RongCloud/c9kqb3rdcj1rj/rc-log.db-shm
src/lib/rust_db/RongCloud/c9kqb3rdcj1rj/rc-log.db-wal
src/lib/rust_db/RongCloud/c9kqb3rdcj1rj/5PmaSCHfI/storage
src/lib/rust_db/RongCloud/c9kqb3rdcj1rj/5PmaSCHfI/storage-shm
src/lib/rust_db/RongCloud/c9kqb3rdcj1rj/5PmaSCHfI/storage-wal
src/lib/rust_db/RongCloud/c9kqb3rdcj1rj/5PmaSCHfI/user.kv
src/lib/rust_db/RongCloud/c9kqb3rdkbb8j/rc-log.db
src/lib/rust_db/RongCloud/c9kqb3rdkbb8j/rc-log.db-shm
src/lib/rust_db/RongCloud/c9kqb3rdkbb8j/rc-log.db-wal
src/lib/rust_db/RongCloud/c9kqb3rdkbb8j/5PmaSCHfI/resend_msg.kv
src/lib/rust_db/RongCloud/c9kqb3rdkbb8j/5PmaSCHfI/storage
src/lib/rust_db/RongCloud/c9kqb3rdkbb8j/5PmaSCHfI/storage-shm
src/lib/rust_db/RongCloud/c9kqb3rdkbb8j/5PmaSCHfI/storage-wal
src/lib/rust_db/RongCloud/c9kqb3rdkbb8j/5PmaSCHfI/user.kv
src/lib/rust_db/RongCloud/n19jmcy59f1q9/rc-log.db
src/lib/rust_db/RongCloud/n19jmcy59f1q9/rc-log.db-shm
src/lib/rust_db/RongCloud/n19jmcy59f1q9/rc-log.db-wal
src/lib/rust_db/RongCloud/n19jmcy59f1q9/5PmaSCHfI/storage
src/lib/rust_db/RongCloud/n19jmcy59f1q9/5PmaSCHfI/storage-shm
src/lib/rust_db/RongCloud/n19jmcy59f1q9/5PmaSCHfI/storage-wal
src/lib/rust_db/RongCloud/n19jmcy59f1q9/5PmaSCHfI/user.kv
src/server/__init__.py
src/server/server.py
src/utils/__init__.py
src/utils/mcp_utils.py
rongcloud_native_mcp_python-0.1.5.dist-info/METADATA
rongcloud_native_mcp_python-0.1.5.dist-info/WHEEL
rongcloud_native_mcp_python-0.1.5.dist-info/entry_points.txt
rongcloud_native_mcp_python-0.1.5.dist-info/RECORD
