Metadata-Version: 2.4
Name: rongcloud-native-mcp-python
Version: 0.1.5
Summary: Rongcloud IM Service based on MCP Protocol (Rust SDK Wrapper)
Author-email: Rongcloud <imsdk@rongcloud.cn>
Requires-Python: >=3.12
Requires-Dist: click>=8.0.0
Requires-Dist: mcp[cli]
Requires-Dist: pydantic
Requires-Dist: pydantic-settings
Requires-Dist: uvicorn
Provides-Extra: dev
Requires-Dist: pip-tools; extra == 'dev'
